README.rst
setup.py
noseapp_selenium/__init__.py
noseapp_selenium/base.py
noseapp_selenium/config.py
noseapp_selenium/drivers.py
noseapp_selenium/proxy.py
noseapp_selenium/tools.py
noseapp_selenium.egg-info/PKG-INFO
noseapp_selenium.egg-info/SOURCES.txt
noseapp_selenium.egg-info/dependency_links.txt
noseapp_selenium.egg-info/not-zip-safe
noseapp_selenium.egg-info/requires.txt
noseapp_selenium.egg-info/top_level.txt
noseapp_selenium/forms/__init__.py
noseapp_selenium/forms/fields.py
noseapp_selenium/forms/group.py
noseapp_selenium/forms/iterators.py
noseapp_selenium/page_object/__init__.py
noseapp_selenium/page_object/base.py
noseapp_selenium/page_object/router.py
noseapp_selenium/page_object/wait.py
noseapp_selenium/query/__init__.py
noseapp_selenium/query/base.py
noseapp_selenium/query/handler.py
noseapp_selenium/query/processor.py
noseapp_selenium/query/result.py