Metadata-Version: 1.1
Name: noseapp-selenium
Version: 1.2.0
Summary: selenium extension for noseapp lib
Home-page: https://github.com/trifonovmixail/noseapp_selenium
Author: Mikhail Trifonov
Author-email: mikhail.trifonov@corp.mail.ru
License: UNKNOWN
Platform: any
Classifier: Development Status :: 4 - Beta
Classifier: Intended Audience :: Developers
Classifier: Operating System :: OS Independent
Classifier: Programming Language :: Python
Classifier: Programming Language :: Python :: 2.7
Classifier: Topic :: Software Development :: Testing
